odoo/addons/test_base_time_window/README.rst
odoo/addons/test_base_time_window/__init__.py
odoo/addons/test_base_time_window/__manifest__.py
odoo/addons/test_base_time_window/i18n/es.po
odoo/addons/test_base_time_window/i18n/test_base_time_window.pot
odoo/addons/test_base_time_window/models/__init__.py
odoo/addons/test_base_time_window/models/partner_time_window.py
odoo/addons/test_base_time_window/models/res_partner.py
odoo/addons/test_base_time_window/readme/CONTRIBUTORS.rst
odoo/addons/test_base_time_window/readme/DESCRIPTION.rst
odoo/addons/test_base_time_window/security/ir.model.access.xml
odoo/addons/test_base_time_window/static/description/icon.png
odoo/addons/test_base_time_window/static/description/index.html
odoo/addons/test_base_time_window/tests/__init__.py
odoo/addons/test_base_time_window/tests/test_base_time_window.py
odoo14_addon_test_base_time_window-14.0.1.0.1.dist-info/METADATA
odoo14_addon_test_base_time_window-14.0.1.0.1.dist-info/WHEEL
odoo14_addon_test_base_time_window-14.0.1.0.1.dist-info/top_level.txt
odoo14_addon_test_base_time_window-14.0.1.0.1.dist-info/RECORD
