Metadata-Version: 2.1
Name: odoo14-addon-test-base-time-window
Version: 14.0.1.0.1
Summary: Test Base model to handle time windows
Home-page: https://github.com/OCA/server-tools
Author: ACSONE SA/NV, Camptocamp, Odoo Community Association (OCA)
Author-email: support@odoo-community.org
License: AGPL-3
Platform: UNKNOWN
Classifier: Programming Language :: Python
Classifier: Framework :: Odoo
Classifier: Framework :: Odoo :: 14.0
Classifier: License :: OSI Approved :: GNU Affero General Public License v3
Requires-Python: >=3.6
Requires-Dist: odoo14-addon-base-time-window
Requires-Dist: odoo (<14.1dev,>=14.0a)
